[1,["237sJmxv1IWonI14I/eoc4","4eQrr73O9NPo5tZhESQnXz"],["root","node","data","_N$skeletonData"],[["sp.SkeletonData",["_name","_atlasText","textureNames","_skeletonJson","textures"],-1,3],["cc.Prefab",["_name"],2],["cc.Node",["_name","_components","_prefab"],2,9,4],["sp.Skeleton",["defaultAnimation","premultipliedAlpha","node","_N$skeletonData"],1,1,6],["cc.PrefabInfo",["fileId","root"],2,1]],[[0,0,1,2,3,4,5],[1,0,2],[2,0,1,2,2],[3,0,1,2,3,3],[4,0,1,2]],[[[[0,"dog_1","\ndog_1.png\nsize: 204,204\nformat: RGBA8888\nfilter: Linear,Linear\nrepeat: none\nD\n  rotate: false\n  xy: 116, 2\n  size: 11, 13\n  orig: 11, 13\n  offset: 0, 0\n  index: -1\nD_copy_3\n  rotate: false\n  xy: 129, 2\n  size: 11, 13\n  orig: 11, 13\n  offset: 0, 0\n  index: -1\near_left\n  rotate: true\n  xy: 113, 125\n  size: 24, 45\n  orig: 24, 45\n  offset: 0, 0\n  index: -1\near_right\n  rotate: true\n  xy: 109, 99\n  size: 24, 45\n  orig: 24, 45\n  offset: 0, 0\n  index: -1\neye_left\n  rotate: false\n  xy: 175, 59\n  size: 21, 19\n  orig: 21, 19\n  offset: 0, 0\n  index: -1\neye_left_close\n  rotate: true\n  xy: 116, 17\n  size: 21, 19\n  orig: 21, 19\n  offset: 0, 0\n  index: -1\neye_right\n  rotate: true\n  xy: 125, 42\n  size: 21, 19\n  orig: 21, 19\n  offset: 0, 0\n  index: -1\neye_right_close\n  rotate: false\n  xy: 146, 38\n  size: 21, 19\n  orig: 21, 19\n  offset: 0, 0\n  index: -1\neyebrow_copy\n  rotate: true\n  xy: 2, 2\n  size: 6, 4\n  orig: 6, 4\n  offset: 0, 0\n  index: -1\neyebrow_right\n  rotate: false\n  xy: 108, 34\n  size: 6, 4\n  orig: 6, 4\n  offset: 0, 0\n  index: -1\nfoot_back_left\n  rotate: false\n  xy: 76, 65\n  size: 23, 15\n  orig: 23, 15\n  offset: 0, 0\n  index: -1\nfoot_back_right\n  rotate: false\n  xy: 101, 65\n  size: 23, 15\n  orig: 23, 15\n  offset: 0, 0\n  index: -1\nfoot_front_left\n  rotate: true\n  xy: 108, 40\n  size: 23, 15\n  orig: 23, 15\n  offset: 0, 0\n  index: -1\nfoot_front_right\n  rotate: false\n  xy: 126, 66\n  size: 23, 15\n  orig: 23, 15\n  offset: 0, 0\n  index: -1\nhead\n  rotate: false\n  xy: 2, 63\n  size: 72, 74\n  orig: 72, 74\n  offset: 0, 0\n  index: -1\nmouth\n  rotate: false\n  xy: 160, 128\n  size: 38, 24\n  orig: 38, 24\n  offset: 0, 0\n  index: -1\nneck\n  rotate: false\n  xy: 109, 83\n  size: 50, 14\n  orig: 50, 14\n  offset: 0, 0\n  index: -1\nnose\n  rotate: false\n  xy: 169, 39\n  size: 20, 18\n  orig: 20, 18\n  offset: 0, 0\n  index: -1\npupil_left\n  rotate: false\n  xy: 191, 46\n  size: 11, 11\n  orig: 11, 11\n  offset: 0, 0\n  index: -1\npupil_right\n  rotate: false\n  xy: 191, 33\n  size: 11, 11\n  orig: 11, 11\n  offset: 0, 0\n  index: -1\nshin_front_right\n  rotate: false\n  xy: 84, 33\n  size: 22, 30\n  orig: 22, 30\n  offset: 0, 0\n  index: -1\nshin_front_right_copy\n  rotate: true\n  xy: 84, 9\n  size: 22, 30\n  orig: 22, 30\n  offset: 0, 0\n  index: -1\nshin_front_right_copy_2\n  rotate: true\n  xy: 160, 104\n  size: 22, 30\n  orig: 22, 30\n  offset: 0, 0\n  index: -1\nshin_front_right_copy_3\n  rotate: true\n  xy: 161, 80\n  size: 22, 30\n  orig: 22, 30\n  offset: 0, 0\n  index: -1\ntail\n  rotate: true\n  xy: 76, 82\n  size: 55, 31\n  orig: 55, 31\n  offset: 0, 0\n  index: -1\nthigh_back_right\n  rotate: false\n  xy: 113, 151\n  size: 43, 51\n  orig: 43, 51\n  offset: 0, 0\n  index: -1\nthigh_back_right_copy\n  rotate: false\n  xy: 2, 10\n  size: 43, 51\n  orig: 43, 51\n  offset: 0, 0\n  index: -1\nthigh_front_right\n  rotate: false\n  xy: 158, 154\n  size: 35, 48\n  orig: 35, 48\n  offset: 0, 0\n  index: -1\nthigh_front_right_copy\n  rotate: false\n  xy: 47, 13\n  size: 35, 48\n  orig: 35, 48\n  offset: 0, 0\n  index: -1\ntorso\n  rotate: false\n  xy: 2, 139\n  size: 109, 63\n  orig: 109, 63\n  offset: 0, 0\n  index: -1\ntounge\n  rotate: true\n  xy: 151, 59\n  size: 19, 22\n  orig: 19, 22\n  offset: 0, 0\n  index: -1\n",["dog_1.png"],{"skeleton":{"hash":"XXVDwzlPYXXkOC4us/52X20D8vg","spine":"3.6.53","width":163.45,"height":165.9,"images":"../Animation/dog_1/"},"bones":[{"name":"root","scaleX":0.7,"scaleY":0.7},{"name":"HEAD","parent":"root","length":98.29,"rotation":89.65,"x":-68.98,"y":123.25},{"name":"EAR_LEFT","parent":"HEAD","length":40.46,"rotation":14.26,"x":72.21,"y":25.43},{"name":"EAR_RIGHT","parent":"HEAD","length":41.99,"rotation":-15.48,"x":73.73,"y":-26.68},{"name":"TORSO","parent":"root","length":117.49,"rotation":0.2,"x":-68.82,"y":102.49},{"name":"THIGH_BACK_LEFT","parent":"TORSO","length":62.16,"rotation":-61.26,"x":79.26,"y":-3.32},{"name":"SHIN_BACK_LEFT","parent":"THIGH_BACK_LEFT","length":27.34,"rotation":-49.5,"x":58.75,"y":-2.87},{"name":"FOOT_BACK_LEFT","parent":"SHIN_BACK_LEFT","length":26.26,"rotation":-67.35,"x":28.09,"y":-1.09},{"name":"THIGH_BACK_RIGHT","parent":"TORSO","length":72.27,"rotation":-63.06,"x":106.14,"y":-2.77},{"name":"SHIN_BACK_RIGHT","parent":"THIGH_BACK_RIGHT","length":29.86,"rotation":-44.6,"x":64.95,"y":-2.36},{"name":"FOOT_BACK_RIGHT","parent":"SHIN_BACK_RIGHT","length":27.91,"rotation":-68.59,"x":29.23,"y":-1.2},{"name":"THIGH_FRONT_LEFT","parent":"TORSO","length":61.51,"rotation":-67.23,"x":-6.83,"y":-6.22},{"name":"SHIN_FRONT_LEFT","parent":"THIGH_FRONT_LEFT","length":26.48,"rotation":-47.98,"x":58.03,"y":-1.65},{"name":"FOOT_FRONT_LEFT","parent":"SHIN_FRONT_LEFT","length":26.27,"rotation":-62.19,"x":26.29,"y":-1.86},{"name":"THIGH_FRONT_RIGHT","parent":"TORSO","length":65.19,"rotation":-68.29,"x":39.56,"y":-9.58},{"name":"SHIN_FRONT_RIGHT","parent":"THIGH_FRONT_RIGHT","length":28.11,"rotation":-44.68,"x":58.29,"y":-1.71},{"name":"FOOT_FRONT_RIGHT","parent":"SHIN_FRONT_RIGHT","length":24.71,"rotation":-62.77,"x":28.98,"y":-2.07},{"name":"PUPIL_LEFT","parent":"HEAD","rotation":-89.65,"x":54.93,"y":16.62},{"name":"PUPIL_RIGHT","parent":"HEAD","x":55.55,"y":-19.87},{"name":"TAIL","parent":"TORSO","length":56.21,"rotation":-14.23,"x":119.1,"y":-0.41},{"name":"TONGUE","parent":"HEAD","length":26.51,"rotation":3.82,"x":-14.69,"y":-9.47}],"slots":[{"name":"shin_front_right_copy_2","bone":"SHIN_FRONT_LEFT","attachment":"shin_front_right_copy_2"},{"name":"foot_front_left","bone":"FOOT_FRONT_LEFT","attachment":"foot_front_left"},{"name":"thigh_front_right_copy","bone":"THIGH_FRONT_LEFT","attachment":"thigh_front_right_copy"},{"name":"shin_front_right_copy_3","bone":"SHIN_BACK_LEFT","attachment":"shin_front_right_copy_3"},{"name":"foot_back_left","bone":"FOOT_BACK_LEFT","attachment":"foot_back_left"},{"name":"thigh_back_right_copy","bone":"THIGH_BACK_LEFT","attachment":"thigh_back_right_copy"},{"name":"tail","bone":"TAIL","attachment":"tail"},{"name":"torso","bone":"TORSO","attachment":"torso"},{"name":"ear_right","bone":"EAR_RIGHT","attachment":"ear_right"},{"name":"ear_left","bone":"EAR_LEFT","attachment":"ear_left"},{"name":"head","bone":"HEAD","attachment":"head"},{"name":"nose","bone":"HEAD","attachment":"nose"},{"name":"mouth","bone":"HEAD","attachment":"mouth"},{"name":"neck","bone":"HEAD","attachment":"neck"},{"name":"tounge","bone":"TONGUE","attachment":"tounge"},{"name":"eye_right","bone":"HEAD","attachment":"eye_right"},{"name":"pupil_right","bone":"PUPIL_RIGHT","attachment":"pupil_right"},{"name":"eyebrow_right","bone":"HEAD","attachment":"eyebrow_right"},{"name":"eye_right_close","bone":"HEAD"},{"name":"D","bone":"HEAD","attachment":"D"},{"name":"D_copy_3","bone":"HEAD","attachment":"D_copy_3"},{"name":"eye_left","bone":"HEAD","attachment":"eye_left"},{"name":"pupil_left","bone":"PUPIL_LEFT","attachment":"pupil_left"},{"name":"eye_left_close","bone":"HEAD"},{"name":"eyebrow_copy","bone":"HEAD","attachment":"eyebrow_copy"},{"name":"shin_front_right","bone":"SHIN_FRONT_RIGHT","attachment":"shin_front_right"},{"name":"foot_front_right","bone":"FOOT_FRONT_RIGHT","attachment":"foot_front_right"},{"name":"shin_front_right_copy","bone":"SHIN_BACK_RIGHT","attachment":"shin_front_right_copy"},{"name":"foot_back_right","bone":"FOOT_BACK_RIGHT","attachment":"foot_back_right"},{"name":"thigh_front_right","bone":"THIGH_FRONT_RIGHT","attachment":"thigh_front_right"},{"name":"thigh_back_right","bone":"THIGH_BACK_RIGHT","attachment":"thigh_back_right"}],"skins":{"default":{"D":{"D":{"x":46.65,"y":-12.58,"rotation":-89.65,"width":15,"height":18}},"D_copy_3":{"D_copy_3":{"x":47.02,"y":7.93,"rotation":-89.65,"width":15,"height":18}},"ear_left":{"ear_left":{"x":9.09,"y":-1.58,"rotation":-103.91,"width":34,"height":64}},"ear_right":{"ear_right":{"x":8.58,"y":-0.92,"rotation":-74.17,"width":34,"height":64}},"eye_left":{"eye_left":{"x":55.47,"y":15.98,"rotation":-89.65,"width":30,"height":27}},"eye_left_close":{"eye_left_close":{"x":55.47,"y":15.98,"rotation":-89.65,"width":30,"height":27}},"eye_right":{"eye_right":{"x":55.69,"y":-20.02,"rotation":-89.65,"width":30,"height":27}},"eye_right_close":{"eye_right_close":{"x":55.69,"y":-20.02,"rotation":-89.65,"width":30,"height":27}},"eyebrow_copy":{"eyebrow_copy":{"x":71.97,"y":16.08,"rotation":-89.65,"width":9,"height":6}},"eyebrow_right":{"eyebrow_right":{"x":72.19,"y":-19.92,"rotation":-89.65,"width":9,"height":6}},"foot_back_left":{"foot_back_left":{"x":10.72,"y":3.01,"rotation":177.9,"width":33,"height":21}},"foot_back_right":{"foot_back_right":{"x":10.68,"y":1.63,"rotation":176.05,"width":33,"height":21}},"foot_front_left":{"foot_front_left":{"x":9.38,"y":1.35,"rotation":177.21,"width":33,"height":21}},"foot_front_right":{"foot_front_right":{"x":8.56,"y":1.42,"rotation":175.54,"width":33,"height":21}},"head":{"head":{"x":48.08,"y":-1.57,"rotation":-89.65,"width":103,"height":105}},"mouth":{"mouth":{"x":15.08,"y":-1.27,"rotation":-89.65,"width":54,"height":34}},"neck":{"neck":{"x":-2.92,"y":-2.38,"rotation":-89.65,"width":71,"height":20}},"nose":{"nose":{"x":30.08,"y":-1.68,"rotation":-89.65,"width":29,"height":25}},"pupil_left":{"pupil_left":{"x":0.64,"y":0.54,"width":15,"height":15}},"pupil_right":{"pupil_right":{"x":0.14,"y":-0.15,"rotation":-89.65,"width":15,"height":15}},"shin_front_right":{"shin_front_right":{"x":15.79,"y":1.15,"rotation":112.77,"width":32,"height":43}},"shin_front_right_copy":{"shin_front_right_copy":{"x":17.15,"y":1.76,"rotation":107.46,"width":32,"height":43}},"shin_front_right_copy_2":{"shin_front_right_copy_2":{"x":13.32,"y":-0.52,"rotation":115.02,"width":32,"height":43}},"shin_front_right_copy_3":{"shin_front_right_copy_3":{"x":17.56,"y":-0.34,"rotation":110.56,"width":32,"height":43}},"tail":{"tail":{"x":26.46,"y":-0.26,"rotation":14.04,"width":78,"height":44}},"thigh_back_right":{"thigh_back_right":{"x":35.3,"y":-7.35,"rotation":62.87,"width":61,"height":73}},"thigh_back_right_copy":{"thigh_back_right_copy":{"x":27.97,"y":-7.54,"rotation":61.06,"width":61,"height":73}},"thigh_front_right":{"thigh_front_right":{"x":31.99,"y":-6.81,"rotation":68.09,"width":50,"height":69}},"thigh_front_right_copy":{"thigh_front_right_copy":{"x":28.52,"y":-5.55,"rotation":67.04,"width":50,"height":69}},"torso":{"torso":{"x":47.64,"y":-17.33,"rotation":-0.2,"width":156,"height":90}},"tounge":{"tounge":{"x":12.22,"y":6.29,"rotation":-93.47,"width":27,"height":32}}}},"animations":{"animation":{"slots":{"eye_left_close":{"attachment":[{"time":0.7333,"name":"eye_left_close"},{"time":0.8,"name":null}]},"eye_right_close":{"attachment":[{"time":0.7333,"name":"eye_right_close"},{"time":0.8,"name":null}]}},"bones":{"root":{"rotate":[{"time":0,"angle":0,"curve":"stepped"},{"time":0.2333,"angle":0,"curve":"stepped"},{"time":0.5,"angle":0,"curve":"stepped"},{"time":0.7333,"angle":0,"curve":"stepped"},{"time":0.9667,"angle":0}],"translate":[{"time":0,"x":0,"y":0,"curve":"stepped"},{"time":0.2333,"x":0,"y":0,"curve":"stepped"},{"time":0.5,"x":0,"y":0,"curve":"stepped"},{"time":0.7333,"x":0,"y":0,"curve":"stepped"},{"time":0.9667,"x":0,"y":0}],"scale":[{"time":0,"x":1,"y":1,"curve":"stepped"},{"time":0.2333,"x":1,"y":1,"curve":"stepped"},{"time":0.5,"x":1,"y":1,"curve":"stepped"},{"time":0.7333,"x":1,"y":1,"curve":"stepped"},{"time":0.9667,"x":1,"y":1}],"shear":[{"time":0,"x":0,"y":0,"curve":"stepped"},{"time":0.2333,"x":0,"y":0,"curve":"stepped"},{"time":0.5,"x":0,"y":0,"curve":"stepped"},{"time":0.7333,"x":0,"y":0,"curve":"stepped"},{"time":0.9667,"x":0,"y":0}]},"HEAD":{"rotate":[{"time":0,"angle":0,"curve":"stepped"},{"time":0.2333,"angle":0,"curve":"stepped"},{"time":0.5,"angle":0,"curve":"stepped"},{"time":0.7333,"angle":0,"curve":"stepped"},{"time":0.9667,"angle":0}],"translate":[{"time":0,"x":0,"y":0,"curve":[0.25,0,0.75,1]},{"time":0.2333,"x":0,"y":3,"curve":[0.25,0,0.75,1]},{"time":0.5,"x":0,"y":0,"curve":[0.25,0,0.75,1]},{"time":0.7333,"x":0,"y":3,"curve":[0.25,0,0.75,1]},{"time":0.9667,"x":0,"y":0}],"scale":[{"time":0,"x":1,"y":1,"curve":"stepped"},{"time":0.2333,"x":1,"y":1,"curve":"stepped"},{"time":0.5,"x":1,"y":1,"curve":"stepped"},{"time":0.7333,"x":1,"y":1,"curve":"stepped"},{"time":0.9667,"x":1,"y":1}],"shear":[{"time":0,"x":0,"y":0,"curve":"stepped"},{"time":0.2333,"x":0,"y":0,"curve":"stepped"},{"time":0.5,"x":0,"y":0,"curve":"stepped"},{"time":0.7333,"x":0,"y":0,"curve":"stepped"},{"time":0.9667,"x":0,"y":0}]},"EAR_RIGHT":{"rotate":[{"time":0,"angle":0,"curve":[0.25,0,0.75,1]},{"time":0.2333,"angle":6.83,"curve":[0.25,0,0.75,1]},{"time":0.5,"angle":0,"curve":[0.25,0,0.75,1]},{"time":0.7333,"angle":3.85,"curve":[0.25,0,0.75,1]},{"time":0.9667,"angle":0}],"translate":[{"time":0,"x":0,"y":0,"curve":"stepped"},{"time":0.2333,"x":0,"y":0,"curve":"stepped"},{"time":0.5,"x":0,"y":0,"curve":"stepped"},{"time":0.7333,"x":0,"y":0,"curve":"stepped"},{"time":0.9667,"x":0,"y":0}],"scale":[{"time":0,"x":1,"y":1,"curve":"stepped"},{"time":0.2333,"x":1,"y":1,"curve":"stepped"},{"time":0.5,"x":1,"y":1,"curve":"stepped"},{"time":0.7333,"x":1,"y":1,"curve":"stepped"},{"time":0.9667,"x":1,"y":1}],"shear":[{"time":0,"x":0,"y":0,"curve":"stepped"},{"time":0.2333,"x":0,"y":0,"curve":"stepped"},{"time":0.5,"x":0,"y":0,"curve":"stepped"},{"time":0.7333,"x":0,"y":0,"curve":"stepped"},{"time":0.9667,"x":0,"y":0}]},"EAR_LEFT":{"rotate":[{"time":0,"angle":0,"curve":[0.25,0,0.75,1]},{"time":0.2333,"angle":-6.37,"curve":[0.25,0,0.75,1]},{"time":0.5,"angle":0,"curve":[0.25,0,0.75,1]},{"time":0.7333,"angle":-4.87,"curve":[0.25,0,0.75,1]},{"time":0.9667,"angle":0}],"translate":[{"time":0,"x":0,"y":0,"curve":"stepped"},{"time":0.2333,"x":0,"y":0,"curve":"stepped"},{"time":0.5,"x":0,"y":0,"curve":"stepped"},{"time":0.7333,"x":0,"y":0,"curve":"stepped"},{"time":0.9667,"x":0,"y":0}],"scale":[{"time":0,"x":1,"y":1,"curve":"stepped"},{"time":0.2333,"x":1,"y":1,"curve":"stepped"},{"time":0.5,"x":1,"y":1,"curve":"stepped"},{"time":0.7333,"x":1,"y":1,"curve":"stepped"},{"time":0.9667,"x":1,"y":1}],"shear":[{"time":0,"x":0,"y":0,"curve":"stepped"},{"time":0.2333,"x":0,"y":0,"curve":"stepped"},{"time":0.5,"x":0,"y":0,"curve":"stepped"},{"time":0.7333,"x":0,"y":0,"curve":"stepped"},{"time":0.9667,"x":0,"y":0}]},"PUPIL_RIGHT":{"rotate":[{"time":0,"angle":0,"curve":"stepped"},{"time":0.2333,"angle":0,"curve":"stepped"},{"time":0.5,"angle":0,"curve":"stepped"},{"time":0.7333,"angle":0,"curve":"stepped"},{"time":0.9667,"angle":0}],"translate":[{"time":0,"x":0,"y":0,"curve":"stepped"},{"time":0.2333,"x":0,"y":0,"curve":"stepped"},{"time":0.4,"x":0,"y":0,"curve":[0.245,0,0.564,1]},{"time":0.5333,"x":4.09,"y":-2.01,"curve":"stepped"},{"time":0.8667,"x":4.09,"y":-2.01,"curve":[0.381,0.55,0.742,1]},{"time":0.9667,"x":0,"y":0}],"scale":[{"time":0,"x":1,"y":1,"curve":"stepped"},{"time":0.2333,"x":1,"y":1,"curve":"stepped"},{"time":0.5,"x":1,"y":1,"curve":"stepped"},{"time":0.7333,"x":1,"y":1,"curve":"stepped"},{"time":0.9667,"x":1,"y":1}],"shear":[{"time":0,"x":0,"y":0,"curve":"stepped"},{"time":0.2333,"x":0,"y":0,"curve":"stepped"},{"time":0.5,"x":0,"y":0,"curve":"stepped"},{"time":0.7333,"x":0,"y":0,"curve":"stepped"},{"time":0.9667,"x":0,"y":0}]},"PUPIL_LEFT":{"rotate":[{"time":0,"angle":0,"curve":"stepped"},{"time":0.2333,"angle":0,"curve":"stepped"},{"time":0.5,"angle":0,"curve":"stepped"},{"time":0.7333,"angle":0,"curve":"stepped"},{"time":0.9667,"angle":0}],"translate":[{"time":0,"x":0,"y":0,"curve":"stepped"},{"time":0.2333,"x":0,"y":0,"curve":"stepped"},{"time":0.4,"x":0,"y":0,"curve":[0.245,0,0.765,1]},{"time":0.5333,"x":3.8,"y":-2.6,"curve":"stepped"},{"time":0.8667,"x":3.8,"y":-2.6,"curve":[0.381,0.55,0.742,1]},{"time":0.9667,"x":0,"y":0}],"scale":[{"time":0,"x":1,"y":1,"curve":"stepped"},{"time":0.2333,"x":1,"y":1,"curve":"stepped"},{"time":0.5,"x":1,"y":1,"curve":"stepped"},{"time":0.7333,"x":1,"y":1,"curve":"stepped"},{"time":0.9667,"x":1,"y":1}],"shear":[{"time":0,"x":0,"y":0,"curve":"stepped"},{"time":0.2333,"x":0,"y":0,"curve":"stepped"},{"time":0.5,"x":0,"y":0,"curve":"stepped"},{"time":0.7333,"x":0,"y":0,"curve":"stepped"},{"time":0.9667,"x":0,"y":0}]},"TONGUE":{"rotate":[{"time":0,"angle":0,"curve":"stepped"},{"time":0.2333,"angle":0,"curve":"stepped"},{"time":0.5,"angle":0,"curve":"stepped"},{"time":0.7333,"angle":0,"curve":"stepped"},{"time":0.9667,"angle":0}],"translate":[{"time":0,"x":-5,"y":-0.03,"curve":[0.25,0,0.75,1]},{"time":0.2333,"x":0,"y":0,"curve":[0.25,0,0.75,1]},{"time":0.5,"x":-5,"y":-0.03,"curve":[0.25,0,0.75,1]},{"time":0.7333,"x":0,"y":0,"curve":[0.25,0,0.75,1]},{"time":0.9667,"x":-5,"y":-0.03}],"scale":[{"time":0,"x":1.195,"y":1,"curve":[0.25,0,0.75,1]},{"time":0.2333,"x":1,"y":1,"curve":[0.25,0,0.75,1]},{"time":0.5,"x":1.195,"y":1,"curve":[0.25,0,0.75,1]},{"time":0.7333,"x":1,"y":1,"curve":[0.25,0,0.75,1]},{"time":0.9667,"x":1.195,"y":1}],"shear":[{"time":0,"x":0,"y":0,"curve":"stepped"},{"time":0.2333,"x":0,"y":0,"curve":"stepped"},{"time":0.5,"x":0,"y":0,"curve":"stepped"},{"time":0.7333,"x":0,"y":0,"curve":"stepped"},{"time":0.9667,"x":0,"y":0}]},"TORSO":{"rotate":[{"time":0,"angle":0,"curve":"stepped"},{"time":0.2333,"angle":0,"curve":"stepped"},{"time":0.5,"angle":0,"curve":"stepped"},{"time":0.7333,"angle":0,"curve":"stepped"},{"time":0.9667,"angle":0}],"translate":[{"time":0,"x":0,"y":0,"curve":[0.25,0,0.75,1]},{"time":0.2333,"x":0,"y":3,"curve":[0.25,0,0.75,1]},{"time":0.5,"x":0,"y":0,"curve":[0.25,0,0.75,1]},{"time":0.7333,"x":0,"y":3,"curve":[0.25,0,0.75,1]},{"time":0.9667,"x":0,"y":0}],"scale":[{"time":0,"x":1,"y":1,"curve":"stepped"},{"time":0.2333,"x":1,"y":1,"curve":"stepped"},{"time":0.5,"x":1,"y":1,"curve":"stepped"},{"time":0.7333,"x":1,"y":1,"curve":"stepped"},{"time":0.9667,"x":1,"y":1}],"shear":[{"time":0,"x":0,"y":0,"curve":"stepped"},{"time":0.2333,"x":0,"y":0,"curve":"stepped"},{"time":0.5,"x":0,"y":0,"curve":"stepped"},{"time":0.7333,"x":0,"y":0,"curve":"stepped"},{"time":0.9667,"x":0,"y":0}]},"TAIL":{"rotate":[{"time":0,"angle":0,"curve":[0.25,0,0.75,1]},{"time":0.2333,"angle":-11.21,"curve":[0.25,0,0.75,1]},{"time":0.5,"angle":0,"curve":[0.25,0,0.75,1]},{"time":0.7333,"angle":-15.32,"curve":[0.25,0,0.75,1]},{"time":0.9667,"angle":0}],"translate":[{"time":0,"x":0,"y":0,"curve":"stepped"},{"time":0.2333,"x":0,"y":0,"curve":"stepped"},{"time":0.5,"x":0,"y":0,"curve":"stepped"},{"time":0.7333,"x":0,"y":0,"curve":"stepped"},{"time":0.9667,"x":0,"y":0}],"scale":[{"time":0,"x":1,"y":1,"curve":"stepped"},{"time":0.2333,"x":1,"y":1,"curve":"stepped"},{"time":0.5,"x":1,"y":1,"curve":"stepped"},{"time":0.7333,"x":1,"y":1,"curve":"stepped"},{"time":0.9667,"x":1,"y":1}],"shear":[{"time":0,"x":0,"y":0,"curve":"stepped"},{"time":0.2333,"x":0,"y":0,"curve":"stepped"},{"time":0.5,"x":0,"y":0,"curve":"stepped"},{"time":0.7333,"x":0,"y":0,"curve":"stepped"},{"time":0.9667,"x":0,"y":0}]},"THIGH_BACK_RIGHT":{"rotate":[{"time":0,"angle":-16.23,"curve":[0.25,0,0.75,1]},{"time":0.2333,"angle":-22.06,"curve":[0.25,0,0.75,1]},{"time":0.5,"angle":-33.38,"curve":[0.25,0,0.75,1]},{"time":0.7333,"angle":-23.87,"curve":[0.25,0,0.75,1]},{"time":0.9667,"angle":-16.23}],"translate":[{"time":0,"x":0,"y":0,"curve":[0.25,0,0.75,1]},{"time":0.2333,"x":-1.58,"y":6.96,"curve":[0.25,0,0.75,1]},{"time":0.5,"x":0.43,"y":1.68,"curve":[0.25,0,0.75,1]},{"time":0.7333,"x":1.71,"y":-0.05,"curve":[0.25,0,0.75,1]},{"time":0.9667,"x":0,"y":0}],"scale":[{"time":0,"x":1,"y":1,"curve":"stepped"},{"time":0.2333,"x":1,"y":1,"curve":"stepped"},{"time":0.5,"x":1,"y":1,"curve":"stepped"},{"time":0.7333,"x":1,"y":1,"curve":"stepped"},{"time":0.9667,"x":1,"y":1}],"shear":[{"time":0,"x":0,"y":0,"curve":"stepped"},{"time":0.2333,"x":0,"y":0,"curve":"stepped"},{"time":0.5,"x":0,"y":0,"curve":"stepped"},{"time":0.7333,"x":0,"y":0,"curve":"stepped"},{"time":0.9667,"x":0,"y":0}]},"SHIN_BACK_RIGHT":{"rotate":[{"time":0,"angle":98.02,"curve":[0.25,0,0.75,1]},{"time":0.2333,"angle":44.72,"curve":[0.25,0,0.75,1]},{"time":0.5,"angle":76.4,"curve":[0.25,0,0.75,1]},{"time":0.7333,"angle":86.74,"curve":[0.25,0,0.75,1]},{"time":0.9667,"angle":98.02}],"translate":[{"time":0,"x":0,"y":0,"curve":"stepped"},{"time":0.2333,"x":0,"y":0,"curve":"stepped"},{"time":0.5,"x":0,"y":0,"curve":"stepped"},{"time":0.7333,"x":0,"y":0,"curve":"stepped"},{"time":0.9667,"x":0,"y":0}],"scale":[{"time":0,"x":1,"y":1,"curve":"stepped"},{"time":0.2333,"x":1,"y":1,"curve":"stepped"},{"time":0.5,"x":1,"y":1,"curve":"stepped"},{"time":0.7333,"x":1,"y":1,"curve":"stepped"},{"time":0.9667,"x":1,"y":1}],"shear":[{"time":0,"x":0,"y":0,"curve":"stepped"},{"time":0.2333,"x":0,"y":0,"curve":"stepped"},{"time":0.5,"x":0,"y":0,"curve":"stepped"},{"time":0.7333,"x":0,"y":0,"curve":"stepped"},{"time":0.9667,"x":0,"y":0}]},"FOOT_BACK_RIGHT":{"rotate":[{"time":0,"angle":-22.27,"curve":"stepped"},{"time":0.2333,"angle":-22.27,"curve":[0.25,0,0.75,1]},{"time":0.5,"angle":-35.61,"curve":[0.25,0,0.75,1]},{"time":0.7333,"angle":-50.19,"curve":[0.25,0,0.75,1]},{"time":0.9667,"angle":-22.27}],"translate":[{"time":0,"x":0,"y":0,"curve":"stepped"},{"time":0.2333,"x":0,"y":0,"curve":"stepped"},{"time":0.5,"x":0,"y":0,"curve":"stepped"},{"time":0.7333,"x":0,"y":0,"curve":"stepped"},{"time":0.9667,"x":0,"y":0}],"scale":[{"time":0,"x":1,"y":1,"curve":"stepped"},{"time":0.2333,"x":1,"y":1,"curve":"stepped"},{"time":0.5,"x":1,"y":1,"curve":"stepped"},{"time":0.7333,"x":1,"y":1,"curve":"stepped"},{"time":0.9667,"x":1,"y":1}],"shear":[{"time":0,"x":0,"y":0,"curve":"stepped"},{"time":0.2333,"x":0,"y":0,"curve":"stepped"},{"time":0.5,"x":0,"y":0,"curve":"stepped"},{"time":0.7333,"x":0,"y":0,"curve":"stepped"},{"time":0.9667,"x":0,"y":0}]},"THIGH_FRONT_RIGHT":{"rotate":[{"time":0,"angle":0,"curve":[0.25,0,0.75,1]},{"time":0.2333,"angle":-5.74,"curve":[0.25,0,0.75,1]},{"time":0.5,"angle":-12.86,"curve":[0.25,0,0.75,1]},{"time":0.7333,"angle":-6.52,"curve":[0.25,0,0.75,1]},{"time":0.9667,"angle":0}],"translate":[{"time":0,"x":0,"y":0,"curve":[0.25,0,0.75,1]},{"time":0.2333,"x":-0.5,"y":5.13,"curve":[0.25,0,0.75,1]},{"time":0.5,"x":0,"y":0,"curve":"stepped"},{"time":0.7333,"x":0,"y":0,"curve":"stepped"},{"time":0.9667,"x":0,"y":0}],"scale":[{"time":0,"x":1,"y":1,"curve":"stepped"},{"time":0.2333,"x":1,"y":1,"curve":"stepped"},{"time":0.5,"x":1,"y":1,"curve":"stepped"},{"time":0.7333,"x":1,"y":1,"curve":"stepped"},{"time":0.9667,"x":1,"y":1}],"shear":[{"time":0,"x":0,"y":0,"curve":"stepped"},{"time":0.2333,"x":0,"y":0,"curve":"stepped"},{"time":0.5,"x":0,"y":0,"curve":"stepped"},{"time":0.7333,"x":0,"y":0,"curve":"stepped"},{"time":0.9667,"x":0,"y":0}]},"SHIN_FRONT_RIGHT":{"rotate":[{"time":0,"angle":39.41,"curve":[0.25,0,0.75,1]},{"time":0.2333,"angle":-9.67,"curve":[0.25,0,0.75,1]},{"time":0.5,"angle":5.79,"curve":[0.25,0,0.75,1]},{"time":0.7333,"angle":36.39,"curve":[0.25,0,0.75,1]},{"time":0.9667,"angle":39.41}],"translate":[{"time":0,"x":0,"y":0,"curve":"stepped"},{"time":0.2333,"x":0,"y":0,"curve":"stepped"},{"time":0.5,"x":0,"y":0,"curve":"stepped"},{"time":0.7333,"x":0,"y":0,"curve":"stepped"},{"time":0.9667,"x":0,"y":0}],"scale":[{"time":0,"x":1,"y":1,"curve":"stepped"},{"time":0.2333,"x":1,"y":1,"curve":"stepped"},{"time":0.5,"x":1,"y":1,"curve":"stepped"},{"time":0.7333,"x":1,"y":1,"curve":"stepped"},{"time":0.9667,"x":1,"y":1}],"shear":[{"time":0,"x":0,"y":0,"curve":"stepped"},{"time":0.2333,"x":0,"y":0,"curve":"stepped"},{"time":0.5,"x":0,"y":0,"curve":"stepped"},{"time":0.7333,"x":0,"y":0,"curve":"stepped"},{"time":0.9667,"x":0,"y":0}]},"FOOT_FRONT_RIGHT":{"rotate":[{"time":0,"angle":-36.32,"curve":[0.25,0,0.75,1]},{"time":0.2333,"angle":22.26,"curve":[0.25,0,0.75,1]},{"time":0.5,"angle":12.98,"curve":[0.25,0,0.75,1]},{"time":0.7333,"angle":-26.77,"curve":[0.25,0,0.75,1]},{"time":0.9667,"angle":-36.32}],"translate":[{"time":0,"x":0,"y":0,"curve":"stepped"},{"time":0.2333,"x":0,"y":0,"curve":"stepped"},{"time":0.5,"x":0,"y":0,"curve":"stepped"},{"time":0.7333,"x":0,"y":0,"curve":"stepped"},{"time":0.9667,"x":0,"y":0}],"scale":[{"time":0,"x":1,"y":1,"curve":"stepped"},{"time":0.2333,"x":1,"y":1,"curve":"stepped"},{"time":0.5,"x":1,"y":1,"curve":"stepped"},{"time":0.7333,"x":1,"y":1,"curve":"stepped"},{"time":0.9667,"x":1,"y":1}],"shear":[{"time":0,"x":0,"y":0,"curve":"stepped"},{"time":0.2333,"x":0,"y":0,"curve":"stepped"},{"time":0.5,"x":0,"y":0,"curve":"stepped"},{"time":0.7333,"x":0,"y":0,"curve":"stepped"},{"time":0.9667,"x":0,"y":0}]},"THIGH_BACK_LEFT":{"rotate":[{"time":0,"angle":0,"curve":[0.25,0,0.75,1]},{"time":0.2333,"angle":-0.35,"curve":[0.25,0,0.75,1]},{"time":0.5,"angle":-3.69,"curve":[0.25,0,0.75,1]},{"time":0.7333,"angle":-31.51,"curve":[0.25,0,0.75,1]},{"time":0.9667,"angle":0}],"translate":[{"time":0,"x":-1.07,"y":2.16,"curve":[0.25,0,0.75,1]},{"time":0.2333,"x":1.95,"y":-1.26,"curve":"stepped"},{"time":0.5,"x":1.95,"y":-1.26,"curve":[0.25,0,0.75,1]},{"time":0.7333,"x":6.27,"y":3.44,"curve":[0.25,0,0.75,1]},{"time":0.9667,"x":-1.07,"y":2.16}],"scale":[{"time":0,"x":1,"y":1,"curve":"stepped"},{"time":0.2333,"x":1,"y":1,"curve":"stepped"},{"time":0.5,"x":1,"y":1,"curve":"stepped"},{"time":0.7333,"x":1,"y":1,"curve":"stepped"},{"time":0.9667,"x":1,"y":1}],"shear":[{"time":0,"x":0,"y":0,"curve":"stepped"},{"time":0.2333,"x":0,"y":0,"curve":"stepped"},{"time":0.5,"x":0,"y":0,"curve":"stepped"},{"time":0.7333,"x":0,"y":0,"curve":"stepped"},{"time":0.9667,"x":0,"y":0}]},"SHIN_BACK_LEFT":{"rotate":[{"time":0,"angle":31.78,"curve":[0.25,0,0.75,1]},{"time":0.2333,"angle":47.64,"curve":[0.25,0,0.75,1]},{"time":0.5,"angle":84.4,"curve":[0.25,0,0.75,1]},{"time":0.7333,"angle":69.57,"curve":[0.25,0,0.75,1]},{"time":0.9667,"angle":31.78}],"translate":[{"time":0,"x":0,"y":0,"curve":"stepped"},{"time":0.2333,"x":0,"y":0,"curve":"stepped"},{"time":0.5,"x":0,"y":0,"curve":[0.25,0,0.75,1]},{"time":0.7333,"x":-0.71,"y":1.78,"curve":[0.25,0,0.75,1]},{"time":0.9667,"x":0,"y":0}],"scale":[{"time":0,"x":1,"y":1,"curve":"stepped"},{"time":0.2333,"x":1,"y":1,"curve":"stepped"},{"time":0.5,"x":1,"y":1,"curve":"stepped"},{"time":0.7333,"x":1,"y":1,"curve":"stepped"},{"time":0.9667,"x":1,"y":1}],"shear":[{"time":0,"x":0,"y":0,"curve":"stepped"},{"time":0.2333,"x":0,"y":0,"curve":"stepped"},{"time":0.5,"x":0,"y":0,"curve":"stepped"},{"time":0.7333,"x":0,"y":0,"curve":"stepped"},{"time":0.9667,"x":0,"y":0}]},"FOOT_BACK_LEFT":{"rotate":[{"time":0,"angle":-26.31,"curve":[0.25,0,0.75,1]},{"time":0.2333,"angle":-39.73,"curve":[0.25,0,0.75,1]},{"time":0.5,"angle":-42.76,"curve":[0.25,0,0.75,1]},{"time":0.7333,"angle":-26.24,"curve":[0.25,0,0.75,1]},{"time":0.9667,"angle":-26.31}],"translate":[{"time":0,"x":0,"y":0,"curve":"stepped"},{"time":0.2333,"x":0,"y":0,"curve":"stepped"},{"time":0.5,"x":0,"y":0,"curve":"stepped"},{"time":0.7333,"x":0,"y":0,"curve":"stepped"},{"time":0.9667,"x":0,"y":0}],"scale":[{"time":0,"x":1,"y":1,"curve":"stepped"},{"time":0.2333,"x":1,"y":1,"curve":"stepped"},{"time":0.5,"x":1,"y":1,"curve":"stepped"},{"time":0.7333,"x":1,"y":1,"curve":"stepped"},{"time":0.9667,"x":1,"y":1}],"shear":[{"time":0,"x":0,"y":0,"curve":"stepped"},{"time":0.2333,"x":0,"y":0,"curve":"stepped"},{"time":0.5,"x":0,"y":0,"curve":"stepped"},{"time":0.7333,"x":0,"y":0,"curve":"stepped"},{"time":0.9667,"x":0,"y":0}]},"THIGH_FRONT_LEFT":{"rotate":[{"time":0,"angle":-11.81,"curve":[0.25,0,0.75,1]},{"time":0.2333,"angle":-4.29,"curve":[0.25,0,0.75,1]},{"time":0.5,"angle":2,"curve":[0.25,0,0.75,1]},{"time":0.7333,"angle":-11.42,"curve":[0.25,0,0.75,1]},{"time":0.9667,"angle":-11.81}],"translate":[{"time":0,"x":0,"y":0,"curve":[0.25,0,0.75,1]},{"time":0.2333,"x":-2.66,"y":5.36,"curve":[0.25,0,0.75,1]},{"time":0.5,"x":0.99,"y":3.72,"curve":"stepped"},{"time":0.7333,"x":0.99,"y":3.72,"curve":[0.25,0,0.75,1]},{"time":0.9667,"x":0,"y":0}],"scale":[{"time":0,"x":1,"y":1,"curve":"stepped"},{"time":0.2333,"x":1,"y":1,"curve":"stepped"},{"time":0.5,"x":1,"y":1,"curve":"stepped"},{"time":0.7333,"x":1,"y":1,"curve":"stepped"},{"time":0.9667,"x":1,"y":1}],"shear":[{"time":0,"x":0,"y":0,"curve":"stepped"},{"time":0.2333,"x":0,"y":0,"curve":"stepped"},{"time":0.5,"x":0,"y":0,"curve":"stepped"},{"time":0.7333,"x":0,"y":0,"curve":"stepped"},{"time":0.9667,"x":0,"y":0}]},"SHIN_FRONT_LEFT":{"rotate":[{"time":0,"angle":0,"curve":[0.25,0,0.75,1]},{"time":0.2333,"angle":33.94,"curve":[0.25,0,0.75,1]},{"time":0.5,"angle":29.24,"curve":[0.25,0,0.75,1]},{"time":0.7333,"angle":0.74,"curve":[0.25,0,0.75,1]},{"time":0.9667,"angle":0}],"translate":[{"time":0,"x":0,"y":0,"curve":"stepped"},{"time":0.2333,"x":0,"y":0,"curve":"stepped"},{"time":0.5,"x":0,"y":0,"curve":"stepped"},{"time":0.7333,"x":0,"y":0,"curve":"stepped"},{"time":0.9667,"x":0,"y":0}],"scale":[{"time":0,"x":1,"y":1,"curve":"stepped"},{"time":0.2333,"x":1,"y":1,"curve":"stepped"},{"time":0.5,"x":1,"y":1,"curve":"stepped"},{"time":0.7333,"x":1,"y":1,"curve":"stepped"},{"time":0.9667,"x":1,"y":1}],"shear":[{"time":0,"x":0,"y":0,"curve":"stepped"},{"time":0.2333,"x":0,"y":0,"curve":"stepped"},{"time":0.5,"x":0,"y":0,"curve":"stepped"},{"time":0.7333,"x":0,"y":0,"curve":"stepped"},{"time":0.9667,"x":0,"y":0}]},"FOOT_FRONT_LEFT":{"rotate":[{"time":0,"angle":11.17,"curve":[0.25,0,0.75,1]},{"time":0.2333,"angle":-23.71,"curve":[0.25,0,0.75,1]},{"time":0.5,"angle":-20.41,"curve":[0.25,0,0.75,1]},{"time":0.7333,"angle":2.67,"curve":[0.25,0,0.75,1]},{"time":0.9667,"angle":11.17}],"translate":[{"time":0,"x":0,"y":0,"curve":"stepped"},{"time":0.2333,"x":0,"y":0,"curve":"stepped"},{"time":0.5,"x":0,"y":0,"curve":"stepped"},{"time":0.7333,"x":0,"y":0,"curve":"stepped"},{"time":0.9667,"x":0,"y":0}],"scale":[{"time":0,"x":1,"y":1,"curve":"stepped"},{"time":0.2333,"x":1,"y":1,"curve":"stepped"},{"time":0.5,"x":1,"y":1,"curve":"stepped"},{"time":0.7333,"x":1,"y":1,"curve":"stepped"},{"time":0.9667,"x":1,"y":1}],"shear":[{"time":0,"x":0,"y":0,"curve":"stepped"},{"time":0.2333,"x":0,"y":0,"curve":"stepped"},{"time":0.5,"x":0,"y":0,"curve":"stepped"},{"time":0.7333,"x":0,"y":0,"curve":"stepped"},{"time":0.9667,"x":0,"y":0}]}}}}},[0]]],0,0,[0],[-1],[0]],[[[1,"dog_1"],[2,"dog",[[3,"animation",false,-2,0]],[4,"5d29gQDRdG+qGfwZweW6QE",-1]]],0,[0,0,1,0,1,1,0,2,1,2],[0],[3],[1]]]]